jppype/__init__.py
jppype/_frontend.py
jppype/_version.py
jppype/layer_base.py
jppype/layers_2d.py
jppype/utils.py
jppype/view2d.py
jppype/labextension/package.json
jppype/labextension/static/122.edfd1a65a79c19915c6c.js
jppype/labextension/static/158.553ea4cbd22b8b5b0bcd.js
jppype/labextension/static/171.0df5a68245df50ccb81e.js
jppype/labextension/static/196.f0f10182d2192efa3f86.js
jppype/labextension/static/196.f0f10182d2192efa3f86.js.LICENSE.txt
jppype/labextension/static/261.1a494909fdd419821b6d.js
jppype/labextension/static/282.170a90713361ffeb4ab6.js
jppype/labextension/static/338.59376e751c503700b695.js
jppype/labextension/static/338.59376e751c503700b695.js.LICENSE.txt
jppype/labextension/static/378.fe125d637c2beeca2278.js
jppype/labextension/static/550.7bb9a6b87ac19a25a263.js
jppype/labextension/static/568.419531d8c3941fea73ab.js
jppype/labextension/static/591.a622eb2396f657c52afa.js
jppype/labextension/static/591.a622eb2396f657c52afa.js.LICENSE.txt
jppype/labextension/static/638.ec1aced46156dd8ec7b7.js
jppype/labextension/static/686.c94e5606f781fea1df9b.js
jppype/labextension/static/686.c94e5606f781fea1df9b.js.LICENSE.txt
jppype/labextension/static/846.8a9b599d33e81e8e8717.js
jppype/labextension/static/remoteEntry.cc2dd5da965245d731d0.js
jppype/labextension/static/style.js
jppype/labextension/static/third-party-licenses.json
jppype/nbextension/index.js
jppype/nbextension/index.js.LICENSE.txt
jppype-0.1.1.1.data/data/share/jupyter/labextensions/jppype/package.json
jppype-0.1.1.1.data/data/share/jupyter/labextensions/jppype/static/122.edfd1a65a79c19915c6c.js
jppype-0.1.1.1.data/data/share/jupyter/labextensions/jppype/static/158.553ea4cbd22b8b5b0bcd.js
jppype-0.1.1.1.data/data/share/jupyter/labextensions/jppype/static/171.0df5a68245df50ccb81e.js
jppype-0.1.1.1.data/data/share/jupyter/labextensions/jppype/static/196.f0f10182d2192efa3f86.js
jppype-0.1.1.1.data/data/share/jupyter/labextensions/jppype/static/196.f0f10182d2192efa3f86.js.LICENSE.txt
jppype-0.1.1.1.dist-info/METADATA
jppype-0.1.1.1.dist-info/WHEEL
jppype-0.1.1.1.dist-info/licenses/LICENSE
jppype-0.1.1.1.dist-info/RECORD
