Metadata-Version: 2.1
Name: jppype
Version: 0.1.1.1
Summary: JupyterLab extension adding data visualisation widgets.
Project-URL: Homepage,  https://github.com/gabriel-lepetitaimon/jppype
Project-URL: Source, https://github.com/gabriel-lepetitaimon/jppype
Author-email: Gabriel Lepetit-Aimon <gabriel.lepetitaimon@gmail.com>
License: MIT License
License-File: LICENSE
Keywords: IPython,Jupyter,JupyterLab,Widgets
Classifier: Development Status :: 4 - Beta
Classifier: Framework :: IPython
Classifier: Framework :: Jupyter
Classifier: Framework :: Jupyter :: JupyterLab
Classifier: Framework :: Jupyter :: JupyterLab :: 3
Classifier: Framework :: Jupyter :: JupyterLab :: 4
Classifier: Framework :: Jupyter :: JupyterLab :: Extensions
Classifier: Framework :: Jupyter :: JupyterLab :: Extensions :: Prebuilt
Classifier: Intended Audience :: Developers
Classifier: Intended Audience :: Science/Research
Classifier: License :: OSI Approved :: MIT License
Classifier: Programming Language :: Python
Classifier: Programming Language :: Python :: 3
Classifier: Programming Language :: Python :: 3.10
Requires-Python: >=3.10
Requires-Dist: ipykernel~=6.22.0
Requires-Dist: ipywidgets<9,~=8.0.5
Requires-Dist: numpy~=1.23.5
Requires-Dist: opencv-python-headless~=4.7
Requires-Dist: webcolors~=1.13
Provides-Extra: build
Requires-Dist: build; extra == 'build'
Requires-Dist: tbump; extra == 'build'
Provides-Extra: dev
Requires-Dist: jupyterlab~=4.0.0; extra == 'dev'
Provides-Extra: examples
